rubyvenv.py
rubyvenv-1.2.1.dist-info/LICENSE
rubyvenv-1.2.1.dist-info/METADATA
rubyvenv-1.2.1.dist-info/WHEEL
rubyvenv-1.2.1.dist-info/entry_points.txt
rubyvenv-1.2.1.dist-info/top_level.txt
rubyvenv-1.2.1.dist-info/RECORD
