Metadata-Version: 2.1
Name: rubyvenv
Version: 1.2.1
Summary: Create no-hassle ruby "virtualenvs".  No .bashrc, no shims, no cd-magic.
Home-page: https://github.com/asottile/rubyvenv
Author: Anthony Sottile
Author-email: asottile@umich.edu
License: MIT
Classifier: License :: OSI Approved :: MIT License
Classifier: Programming Language :: Python :: 3
Classifier: Programming Language :: Python :: 3 :: Only
Classifier: Programming Language :: Python :: Implementation :: CPython
Classifier: Programming Language :: Python :: Implementation :: PyPy
Requires-Python: >=3.7
License-File: LICENSE
Requires-Dist: distro
